AUTHORS
LICENSE
MANIFEST.in
README.rst
setup.py
tox.ini
docs/Makefile
docs/make.bat
docs/source/api.rst
docs/source/changelog.rst
docs/source/conf.py
docs/source/dev.rst
docs/source/elasticsearch-py.rst
docs/source/features.rst
docs/source/index.rst
docs/source/migrate.rst
pyelasticsearch/__init__.py
pyelasticsearch/client.py
pyelasticsearch/exceptions.py
pyelasticsearch/utils.py
pyelasticsearch.egg-info/PKG-INFO
pyelasticsearch.egg-info/SOURCES.txt
pyelasticsearch.egg-info/dependency_links.txt
pyelasticsearch.egg-info/not-zip-safe
pyelasticsearch.egg-info/requires.txt
pyelasticsearch.egg-info/top_level.txt
pyelasticsearch/tests/__init__.py
pyelasticsearch/tests/client_tests.py
pyelasticsearch/tests/es_kwargs_tests.py
pyelasticsearch/tests/json_tests.py
pyelasticsearch/tests/utils_tests.py