Metadata-Version: 1.1
Name: pyelasticsearch
Version: 1.2.2
Summary: Flexible, high-scale API to elasticsearch
Home-page: https://github.com/pyelasticsearch/pyelasticsearch
Author: Erik Rose
Author-email: erik@mozilla.com
License: BSD
Platform: UNKNOWN
Classifier: Development Status :: 5 - Production/Stable
Classifier: Intended Audience :: Developers
Classifier: License :: OSI Approved :: BSD License
Classifier: Operating System :: OS Independent
Classifier: Programming Language :: Python
Classifier: Programming Language :: Python :: 2
Classifier: Programming Language :: Python :: 2.6
Classifier: Programming Language :: Python :: 2.7
Classifier: Programming Language :: Python :: 3
Classifier: Programming Language :: Python :: 3.3
Classifier: Programming Language :: Python :: 3.4
Classifier: Topic :: Internet :: WWW/HTTP :: Indexing/Search
